chat_cvdpm/__init__.py
chat_cvdpm/agent.py
chat_cvdpm/format.py
chat_cvdpm-0.1.13.dist-info/METADATA
chat_cvdpm-0.1.13.dist-info/WHEEL
chat_cvdpm-0.1.13.dist-info/entry_points.txt
chat_cvdpm-0.1.13.dist-info/RECORD
