Metadata-Version: 2.4
Name: chat-cvdpm
Version: 0.1.13
Summary: Perform analysis using chat interface with CVDPM outputs
Requires-Python: <3.14,>=3.9
Requires-Dist: langchain-anthropic==0.3.22
Requires-Dist: langchain-community==0.3.31
Requires-Dist: langchain-core==0.3.79
Requires-Dist: langchain-experimental==0.3.4
Requires-Dist: langchain-text-splitters==0.3.11
Requires-Dist: langchain==0.3.27
Requires-Dist: langgraph-checkpoint==2.1.2
Requires-Dist: langgraph-prebuilt==0.6.4
Requires-Dist: langgraph-sdk==0.2.9
Requires-Dist: langgraph==0.6.10
Requires-Dist: pandas==2.3.3
Requires-Dist: pyarrow<18.0.0,>=14.0.1
Requires-Dist: pydantic-core==2.33.2
Requires-Dist: pydantic-settings==2.11.0
Requires-Dist: pydantic<2.33,>=2.0
Requires-Dist: typing-extensions==4.15.0
Requires-Dist: typing-inspect==0.9.0
Requires-Dist: typing-inspection==0.4.2
